[{"place_id": 243628395, "licence": "Data \u00a9 OpenStreetMap contributors, ODbL 1.0. http://osm.org/copyright", "osm_type": "way", "osm_id": 4242930, "lat": "51.541275150000004", "lon": "-0.24037518614199443", "class": "leisure", "type": "park", "place_rank": 24, "importance": 0.24232784765903637, "addresstype": "park", "name": "Roundwood Park", "display_name": "Roundwood Park, Harlesden, London Borough of Brent, London, Greater London, England, United Kingdom", "boundingbox": ["51.5389641", "51.5436834", "-0.2428960", "-0.2375144"], "geojson": {"type": "Polygon", "coordinates": [[[-0.242896, 51.5436085], [-0.2427749, 51.5433312], [-0.2426966, 51.5430874], [-0.2427017, 51.5429779], [-0.2427123, 51.5427516], [-0.2427604, 51.5423355], [-0.2427991, 51.5418798], [-0.2428059, 51.5418003], [-0.2427927, 51.5414063], [-0.2426467, 51.5410105], [-0.2425088, 51.540761], [-0.242489, 51.5407237], [-0.2424784, 51.5406714], [-0.2423997, 51.5402827], [-0.2423963, 51.5402487], [-0.242232, 51.5400085], [-0.2419245, 51.5396514], [-0.2417758, 51.5393784], [-0.2415753, 51.5391466], [-0.2414196, 51.5389641], [-0.2407681, 51.5391376], [-0.2406172, 51.5390177], [-0.2401107, 51.5391282], [-0.2400379, 51.5391445], [-0.2392547, 51.539298], [-0.23906, 51.5392772], [-0.2388746, 51.5392305], [-0.2383804, 51.5390811], [-0.2383213, 51.5394247], [-0.2382988, 51.5396733], [-0.2381963, 51.5399398], [-0.2381593, 51.540022], [-0.2383176, 51.5400904], [-0.2383812, 51.5404867], [-0.2380507, 51.5407412], [-0.2377258, 51.5409435], [-0.2375144, 51.5410035], [-0.2378302, 51.5411503], [-0.2381819, 51.5414], [-0.2382033, 51.5416835], [-0.2382743, 51.5419838], [-0.2383481, 51.5424175], [-0.2385037, 51.5427612], [-0.2388216, 51.5430213], [-0.2391027, 51.5433472], [-0.2392, 51.54346], [-0.2394757, 51.5436068], [-0.2400379, 51.5436252], [-0.2406403, 51.5436654], [-0.2409545, 51.5436834], [-0.2413384, 51.5436816], [-0.2417183, 51.5436747], [-0.2420726, 51.5436572], [-0.2423843, 51.543641], [-0.2426643, 51.5436215], [-0.242896, 51.5436085]]]}}, {"place_id": 243058104, "licence": "Data \u00a9 OpenStreetMap contributors, ODbL 1.0. http://osm.org/copyright", "osm_type": "node", "osm_id": 469780479, "lat": "51.5404184", "lon": "-0.2383175", "class": "highway", "type": "bus_stop", "place_rank": 30, "importance": 9.307927061870783e-05, "addresstype": "highway", "name": "Roundwood Park", "display_name": "Roundwood Park, Harlesden Road, Willesden Green, Harlesden, London Borough of Brent, London, Greater London, England, NW10 3RT, United Kingdom", "boundingbox": ["51.5403684", "51.5404684", "-0.2383675", "-0.2382675"], "geojson": {"type": "Point", "coordinates": [-0.2383175, 51.5404184]}}, {"place_id": 244115523, "licence": "Data \u00a9 OpenStreetMap contributors, ODbL 1.0. http://osm.org/copyright", "osm_type": "node", "osm_id": 469780478, "lat": "51.5406954", "lon": "-0.2376013", "class": "highway", "type": "bus_stop", "place_rank": 30, "importance": 9.307927061870783e-05, "addresstype": "highway", "name": "Roundwood Park", "display_name": "Roundwood Park, Harlesden Road, Willesden Green, Harlesden, London Borough of Brent, London, Greater London, England, NW10 3RT, United Kingdom", "boundingbox": ["51.5406454", "51.5407454", "-0.2376513", "-0.2375513"], "geojson": {"type": "Point", "coordinates": [-0.2376013, 51.5406954]}}, {"place_id": 243535980, "licence": "Data \u00a9 OpenStreetMap contributors, ODbL 1.0. http://osm.org/copyright", "osm_type": "node", "osm_id": 469780480, "lat": "51.5402217", "lon": "-0.2377331", "class": "highway", "type": "bus_stop", "place_rank": 30, "importance": 9.307927061870783e-05, "addresstype": "highway", "name": "Roundwood Park", "display_name": "Roundwood Park, Harlesden Road, Willesden Green, Harlesden, London Borough of Brent, London, Greater London, England, NW10 3RT, United Kingdom", "boundingbox": ["51.5401717", "51.5402717", "-0.2377831", "-0.2376831"], "geojson": {"type": "Point", "coordinates": [-0.2377331, 51.5402217]}}]