{"version": 0.6, "generator": "Overpass API 0.7.62.1 084b4234", "osm3s": {"timestamp_osm_base": "2024-08-14T09:40:14Z", "copyright": "The data included in this document is from www.openstreetmap.org. The data is made available under ODbL."}, "elements": [{"type": "node", "id": 20821141, "lat": 51.5024232, "lon": -0.1874572}, {"type": "node", "id": 20821142, "lat": 51.5032407, "lon": -0.1878949, "tags": {"created_by": "JOSM"}}, {"type": "node", "id": 20821143, "lat": 51.5041599, "lon": -0.1883313}, {"type": "node", "id": 20821144, "lat": 51.504369, "lon": -0.1869746}, {"type": "node", "id": 20821146, "lat": 51.505666, "lon": -0.1879458}, {"type": "node", "id": 20821147, "lat": 51.5056552, "lon": -0.1880041}, {"type": "node", "id": 20821152, "lat": 51.5099492, "lon": -0.1899051}, {"type": "node", "id": 20821153, "lat": 51.5099528, "lon": -0.1896895}, {"type": "node", "id": 20821155, "lat": 51.5096749, "lon": -0.1895334}, {"type": "node", "id": 20821156, "lat": 51.5098253, "lon": -0.1879382}, {"type": "node", "id": 20821158, "lat": 51.5100311, "lon": -0.1880229}, {"type": "node", "id": 20821159, "lat": 51.5104426, "lon": -0.1831346}, {"type": "node", "id": 20821161, "lat": 51.5112653, "lon": -0.1775316}, {"type": "node", "id": 20821162, "lat": 51.5116869, "lon": -0.1744998}, {"type": "node", "id": 20821168, "lat": 51.5114545, "lon": -0.1739805}, {"type": "node", "id": 20821169, "lat": 51.5101859, "lon": -0.1710577}, {"type": "node", "id": 20821171, "lat": 51.5070977, "lon": -0.170829}, {"type": "node", "id": 20821172, "lat": 51.5069485, "lon": -0.1718801}, {"type": "node", "id": 20821174, "lat": 51.5067721, "lon": -0.1723538}, {"type": "node", "id": 20821176, "lat": 51.5057347, "lon": -0.1731765}, {"type": "node", "id": 20821177, "lat": 51.5049222, "lon": -0.1736034}, {"type": "node", "id": 20821178, "lat": 51.5036819, "lon": -0.1745459}, {"type": "node", "id": 20821179, "lat": 51.5031299, "lon": -0.1747805}, {"type": "node", "id": 20821180, "lat": 51.5026543, "lon": -0.1748251}, {"type": "node", "id": 20821183, "lat": 51.5016973, "lon": -0.1789469}, {"type": "node", "id": 20821185, "lat": 51.5021166, "lon": -0.1852812}, {"type": "node", "id": 20821188, "lat": 51.5019875, "lon": -0.1699791}, {"type": "node", "id": 20821190, "lat": 51.5022384, "lon": -0.1650162}, {"type": "node", "id": 20821191, "lat": 51.5029094, "lon": -0.1543874}, {"type": "node", "id": 20821192, "lat": 51.5057558, "lon": -0.152169}, {"type": "node", "id": 20821195, "lat": 51.5124197, "lon": -0.1591913}, {"type": "node", "id": 20821196, "lat": 51.5124761, "lon": -0.1612395}, {"type": "node", "id": 20821197, "lat": 51.5128966, "lon": -0.1626298}, {"type": "node", "id": 20821198, "lat": 51.512317, "lon": -0.1676481}, {"type": "node", "id": 20821199, "lat": 51.5109028, "lon": -0.158005}, {"type": "node", "id": 20947304, "lat": 51.5058738, "lon": -0.1730333}, {"type": "node", "id": 20947336, "lat": 51.5018945, "lon": -0.16829}, {"type": "node", "id": 20947337, "lat": 51.5021215, "lon": -0.1682857}, {"type": "node", "id": 20947348, "lat": 51.5027148, "lon": -0.1575946}, {"type": "node", "id": 20947350, "lat": 51.50318, "lon": -0.1526779}, {"type": "node", "id": 20947351, "lat": 51.5033331, "lon": -0.1519621}, {"type": "node", "id": 20947352, "lat": 51.5038553, "lon": -0.1521334}, {"type": "node", "id": 20947353, "lat": 51.5040063, "lon": -0.1522317}, {"type": "node", "id": 21494027, "lat": 51.5114859, "lon": -0.1759067, "tags": {"barrier": "gate", "foot": "permissive", "name": "Marlborough Gate", "opening_hours": "Mo-Su 06:00-18:30", "place": "locality"}}, {"type": "node", "id": 26389825, "lat": 51.5025727, "lon": -0.1585149, "tags": {"access": "no", "barrier": "gate", "bicycle": "yes", "name": "Albert Gate", "place": "locality"}}, {"type": "node", "id": 86119745, "lat": 51.5054813, "lon": -0.1732657}, {"type": "node", "id": 207445792, "lat": 51.5115396, "lon": -0.1740336}, {"type": "node", "id": 207454651, "lat": 51.5112294, "lon": -0.1732495}, {"type": "node", "id": 207458571, "lat": 51.5122619, "lon": -0.1607924}, {"type": "node", "id": 207458574, "lat": 51.5128265, "lon": -0.1616206}, {"type": "node", "id": 207458575, "lat": 51.5129791, "lon": -0.1618519}, {"type": "node", "id": 207460763, "lat": 51.5124055, "lon": -0.1587791}, {"type": "node", "id": 207477691, "lat": 51.5094571, "lon": -0.1707021}, {"type": "node", "id": 207562678, "lat": 51.5020233, "lon": -0.1704495}, {"type": "node", "id": 207605987, "lat": 51.5024468, "lon": -0.1564951}, {"type": "node", "id": 207609221, "lat": 51.5039594, "lon": -0.1515728}, {"type": "node", "id": 207609223, "lat": 51.5042063, "lon": -0.1525189}, {"type": "node", "id": 207609224, "lat": 51.5048857, "lon": -0.1521842}, {"type": "node", "id": 207609226, "lat": 51.5050965, "lon": -0.1523237}, {"type": "node", "id": 207609227, "lat": 51.5061317, "lon": -0.1523749}, {"type": "node", "id": 207610513, "lat": 51.5083098, "lon": -0.1550082}, {"type": "node", "id": 207631298, "lat": 51.5026335, "lon": -0.1558361, "tags": {"access": "no", "barrier": "gate", "name": "White Horse Gate", "place": "locality"}}, {"type": "node", "id": 236952241, "lat": 51.5039569, "lon": -0.1516798}, {"type": "node", "id": 236952243, "lat": 51.503493, "lon": -0.1514099}, {"type": "node", "id": 236952245, "lat": 51.5035206, "lon": -0.1512785}, {"type": "node", "id": 236952247, "lat": 51.5038597, "lon": -0.151393}, {"type": "node", "id": 237012656, "lat": 51.5067653, "lon": -0.1712801}, {"type": "node", "id": 237012663, "lat": 51.5073905, "lon": -0.1705236}, {"type": "node", "id": 237012672, "lat": 51.5072243, "lon": -0.1707425}, {"type": "node", "id": 237012676, "lat": 51.5099464, "lon": -0.1708016}, {"type": "node", "id": 247392315, "lat": 51.5078827, "lon": -0.1543794}, {"type": "node", "id": 247393224, "lat": 51.5098756, "lon": -0.1571967}, {"type": "node", "id": 255681108, "lat": 51.506858, "lon": -0.1721292, "tags": {"barrier": "gate", "bicycle": "no", "foot": "yes", "opening_hours": "Mo-Su 06:00-18:30"}}, {"type": "node", "id": 298299052, "lat": 51.5114097, "lon": -0.1764668}, {"type": "node", "id": 331421031, "lat": 51.5056371, "lon": -0.1879323}, {"type": "node", "id": 331421032, "lat": 51.5049053, "lon": -0.1872354}, {"type": "node", "id": 387796890, "lat": 51.5023351, "lon": -0.1630789}, {"type": "node", "id": 387798023, "lat": 51.502146, "lon": -0.1664608}, {"type": "node", "id": 387798024, "lat": 51.5021397, "lon": -0.1667629}, {"type": "node", "id": 452413249, "lat": 51.5083563, "lon": -0.1550688, "tags": {"access": "yes", "barrier": "gate"}}, {"type": "node", "id": 671350287, "lat": 51.5087697, "lon": -0.1554881}, {"type": "node", "id": 671350344, "lat": 51.5098377, "lon": -0.1571669}, {"type": "node", "id": 671350346, "lat": 51.5094437, "lon": -0.1567513}, {"type": "node", "id": 671360987, "lat": 51.5050823, "lon": -0.152174}, {"type": "node", "id": 725292299, "lat": 51.5051249, "lon": -0.187698}, {"type": "node", "id": 725292334, "lat": 51.5051504, "lon": -0.1875554}, {"type": "node", "id": 725292344, "lat": 51.505244, "lon": -0.1873904}, {"type": "node", "id": 725292429, "lat": 51.5052099, "lon": -0.1875825}, {"type": "node", "id": 734984888, "lat": 51.5089021, "lon": -0.1556993}, {"type": "node", "id": 735473600, "lat": 51.5054648, "lon": -0.1522502}, {"type": "node", "id": 735473604, "lat": 51.5057019, "lon": -0.1522675, "tags": {"barrier": "gate", "bicycle": "dismount", "foot": "yes"}}, {"type": "node", "id": 735473609, "lat": 51.5057432, "lon": -0.1522736}, {"type": "node", "id": 764881525, "lat": 51.5099538, "lon": -0.1897961, "tags": {"barrier": "gate", "bicycle": "no", "name": "Orme Square Gate", "opening_hours": "Mo-Su 06:00-18:30", "place": "locality"}}, {"type": "node", "id": 834349201, "lat": 51.5096939, "lon": -0.1897713}, {"type": "node", "id": 1109765916, "lat": 51.5018785, "lon": -0.1842831, "tags": {"access": "yes", "barrier": "gate", "bicycle": "yes", "foot": "yes", "name": "Palace Gate", "note:opening_hours": "http://www.royalparks.org.uk/docs/kensington/Kensington_Gardens_and_Brompton_Cemetery_Closing_Times_2011.pdf", "opening_hours": "Mo-Su 06:00-18:30", "place": "locality"}}, {"type": "node", "id": 1109765917, "lat": 51.5015706, "lon": -0.1822945, "tags": {"access": "yes", "barrier": "gate", "bicycle": "no", "foot": "yes", "name": "Hyde Park Gate", "note:opening_hours": "http://www.royalparks.org.uk/docs/kensington/Kensington_Gardens_and_Brompton_Cemetery_Closing_Times_2011.pdf", "opening_hours": "Mo-Su 06:00-18:30", "place": "locality"}}, {"type": "node", "id": 1109765920, "lat": 51.501635, "lon": -0.1804476, "tags": {"access": "yes", "barrier": "gate", "bicycle": "yes", "foot": "yes", "horse": "no", "motor_vehicle": "no", "name": "Queen's Gate", "note:opening_hours": "http://www.royalparks.org.uk/docs/kensington/Kensington_Gardens_and_Brompton_Cemetery_Closing_Times_2010.pdf", "opening_hours": "Mo-Su 06:00-18:30", "place": "locality"}}, {"type": "node", "id": 1349324847, "lat": 51.5036584, "lon": -0.1515054}, {"type": "node", "id": 1436218855, "lat": 51.5023987, "lon": -0.1605695, "tags": {"barrier": "gate"}}, {"type": "node", "id": 1436361238, "lat": 51.5015684, "lon": -0.18243}, {"type": "node", "id": 1436361337, "lat": 51.5015601, "lon": -0.1813643}, {"type": "node", "id": 1436367924, "lat": 51.5015651, "lon": -0.1806171}, {"type": "node", "id": 1436368100, "lat": 51.5015544, "lon": -0.1807353}, {"type": "node", "id": 1436408680, "lat": 51.5075873, "lon": -0.170496}, {"type": "node", "id": 1436511736, "lat": 51.5024678, "lon": -0.1874811}, {"type": "node", "id": 1436511768, "lat": 51.5023191, "lon": -0.186575}, {"type": "node", "id": 1436642338, "lat": 51.5113927, "lon": -0.173308}, {"type": "node", "id": 1436642449, "lat": 51.5109088, "lon": -0.1726738}, {"type": "node", "id": 1504531858, "lat": 51.5067637, "lon": -0.1711835}, {"type": "node", "id": 1668567586, "lat": 51.5022983, "lon": -0.1621364}, {"type": "node", "id": 1699764452, "lat": 51.5043117, "lon": -0.1874092}, {"type": "node", "id": 1699764466, "lat": 51.5043619, "lon": -0.1870469}, {"type": "node", "id": 1699764471, "lat": 51.504363, "lon": -0.1874092}, {"type": "node", "id": 1699764478, "lat": 51.5043963, "lon": -0.187358}, {"type": "node", "id": 1699764485, "lat": 51.5044004, "lon": -0.1870795}, {"type": "node", "id": 1699764490, "lat": 51.5044131, "lon": -0.1872875, "tags": {"access": "private", "barrier": "gate"}}, {"type": "node", "id": 1699764500, "lat": 51.5044254, "lon": -0.1871686}, {"type": "node", "id": 1699764523, "lat": 51.5048778, "lon": -0.1872181, "tags": {"access": "private", "barrier": "gate", "opening_hours": "Mo-Su 06:00-18:30"}}, {"type": "node", "id": 1699764531, "lat": 51.5049585, "lon": -0.1872597, "tags": {"barrier": "entrance"}}, {"type": "node", "id": 1699764568, "lat": 51.5051366, "lon": -0.1876333}, {"type": "node", "id": 1699764754, "lat": 51.5067353, "lon": -0.1884747}, {"type": "node", "id": 1737433651, "lat": 51.5065777, "lon": -0.1724556}, {"type": "node", "id": 1737450669, "lat": 51.5066316, "lon": -0.172429}, {"type": "node", "id": 1961861413, "lat": 51.5040392, "lon": -0.1522788, "tags": {"barrier": "gate"}}, {"type": "node", "id": 1961861440, "lat": 51.5041337, "lon": -0.1524213, "tags": {"access": "no", "barrier": "gate"}}, {"type": "node", "id": 1961872705, "lat": 51.5031452, "lon": -0.15266}, {"type": "node", "id": 1961872707, "lat": 51.5031411, "lon": -0.1532618}, {"type": "node", "id": 1961872725, "lat": 51.5031285, "lon": -0.1533764}, {"type": "node", "id": 1973754672, "lat": 51.5039157, "lon": -0.1514603}, {"type": "node", "id": 1973754686, "lat": 51.5040206, "lon": -0.1520254}, {"type": "node", "id": 1973754694, "lat": 51.5042771, "lon": -0.152425}, {"type": "node", "id": 1973787094, "lat": 51.5100875, "lon": -0.170903}, {"type": "node", "id": 1973787095, "lat": 51.5103648, "lon": -0.1713287}, {"type": "node", "id": 1973787097, "lat": 51.5105756, "lon": -0.171825}, {"type": "node", "id": 1973882974, "lat": 51.5020006, "lon": -0.1712566, "tags": {"barrier": "gate", "name": "Kingston Gate"}}, {"type": "node", "id": 1973882995, "lat": 51.5020213, "lon": -0.1700415}, {"type": "node", "id": 1973883218, "lat": 51.5033104, "lon": -0.1747333}, {"type": "node", "id": 1973883240, "lat": 51.5043442, "lon": -0.1740214}, {"type": "node", "id": 1973962705, "lat": 51.5068038, "lon": -0.1710998}, {"type": "node", "id": 1974137909, "lat": 51.5022862, "lon": -0.1622703, "tags": {"barrier": "gate", "bicycle": "permissive", "foot": "yes", "material": "metal", "motor_vehicle": "private", "name": "Edinburgh Gate", "place": "locality"}}, {"type": "node", "id": 1974137921, "lat": 51.5018978, "lon": -0.1684006, "tags": {"barrier": "gate", "name": "Rutland Gate", "place": "locality"}}, {"type": "node", "id": 1974138007, "lat": 51.5022842, "lon": -0.1623734}, {"type": "node", "id": 1974138021, "lat": 51.5023725, "lon": -0.1623785}, {"type": "node", "id": 1974138024, "lat": 51.5023987, "lon": -0.1621466}, {"type": "node", "id": 1974138026, "lat": 51.5023959, "lon": -0.160668}, {"type": "node", "id": 1974138030, "lat": 51.5024007, "lon": -0.1605176}, {"type": "node", "id": 1974138035, "lat": 51.5024971, "lon": -0.160692}, {"type": "node", "id": 1974138064, "lat": 51.5025104, "lon": -0.1605523}, {"type": "node", "id": 1974138067, "lat": 51.502565, "lon": -0.1586517}, {"type": "node", "id": 1974138073, "lat": 51.5025794, "lon": -0.1595524}, {"type": "node", "id": 1974138078, "lat": 51.5025772, "lon": -0.1584237}, {"type": "node", "id": 1974138082, "lat": 51.5026055, "lon": -0.1586652}, {"type": "node", "id": 1974138086, "lat": 51.5026243, "lon": -0.1587076}, {"type": "node", "id": 1974138089, "lat": 51.5026319, "lon": -0.1565021}, {"type": "node", "id": 1974138093, "lat": 51.5026489, "lon": -0.1584366}, {"type": "node", "id": 1974138099, "lat": 51.502767, "lon": -0.1552983}, {"type": "node", "id": 1974138102, "lat": 51.5058981, "lon": -0.1730139}, {"type": "node", "id": 1974253515, "lat": 51.511876, "lon": -0.1724074}, {"type": "node", "id": 1974253518, "lat": 51.5119097, "lon": -0.1720883}, {"type": "node", "id": 1974253521, "lat": 51.5119186, "lon": -0.1720506}, {"type": "node", "id": 2198682903, "lat": 51.5016475, "lon": -0.1802499, "tags": {"barrier": "gate", "bicycle": "yes", "foot": "yes", "motor_vehicle": "permit", "name": "Queen's Gate", "opening_hours": "Mo-Su 06:00-18:30"}}, {"type": "node", "id": 2388382242, "lat": 51.5024988, "lon": -0.171785}, {"type": "node", "id": 2388382243, "lat": 51.5025339, "lon": -0.1667973}, {"type": "node", "id": 2388382244, "lat": 51.5027023, "lon": -0.1644133}, {"type": "node", "id": 2388382245, "lat": 51.5029001, "lon": -0.1717982}, {"type": "node", "id": 2388382246, "lat": 51.503234, "lon": -0.164455}, {"type": "node", "id": 2388382247, "lat": 51.5032727, "lon": -0.1658797}, {"type": "node", "id": 2388382248, "lat": 51.5033204, "lon": -0.1674826}, {"type": "node", "id": 2388382249, "lat": 51.5033765, "lon": -0.1694112}, {"type": "node", "id": 2388382250, "lat": 51.5033394, "lon": -0.1718308}, {"type": "node", "id": 2558339871, "lat": 51.5114907, "lon": -0.1583946}, {"type": "node", "id": 2558339896, "lat": 51.512394, "lon": -0.159571}, {"type": "node", "id": 2686374473, "lat": 51.5019744, "lon": -0.1697486}, {"type": "node", "id": 2686374474, "lat": 51.501966, "lon": -0.1696001}, {"type": "node", "id": 2763549311, "lat": 51.5115772, "lon": -0.1740562}, {"type": "node", "id": 2837760387, "lat": 51.5025706, "lon": -0.158578, "tags": {"access": "no", "barrier": "gate", "name": "Albert Gate"}}, {"type": "node", "id": 2837760388, "lat": 51.5025752, "lon": -0.1584649, "tags": {"access": "no", "barrier": "gate", "foot": "no", "name": "Albert Gate"}}, {"type": "node", "id": 3034935545, "lat": 51.502543, "lon": -0.1600805, "tags": {"access": "customers", "barrier": "gate", "source": "Survey of 2014-08-22"}}, {"type": "node", "id": 3054882685, "lat": 51.5041396, "lon": -0.1883208, "tags": {"barrier": "gate", "bicycle": "dismount", "foot": "yes", "name": "Studio Gate", "opening_hours": "Mo-Su 06:00-18:30", "place": "locality"}}, {"type": "node", "id": 3073841718, "lat": 51.5124538, "lon": -0.1665289, "tags": {"barrier": "gate", "name": "Albion Gate", "place": "locality"}}, {"type": "node", "id": 3287719969, "lat": 51.511876, "lon": -0.1722728, "tags": {"barrier": "gate", "name": "Victoria Gate", "place": "locality", "source": "Survey of 2015-01-14"}}, {"type": "node", "id": 3287719970, "lat": 51.5118829, "lon": -0.1721764, "tags": {"barrier": "gate", "name": "Victoria Gate", "source": "Survey of 2015-01-14"}}, {"type": "node", "id": 3679163773, "lat": 51.5101028, "lon": -0.1870743, "tags": {"barrier": "gate", "opening_hours": "Mo-Su 06:00-18:30"}}, {"type": "node", "id": 3679163785, "lat": 51.5101242, "lon": -0.1867731, "tags": {"barrier": "gate", "opening_hours": "Mo-Su 06:00-18:30"}}, {"type": "node", "id": 3679166320, "lat": 51.5103994, "lon": -0.1836208, "tags": {"barrier": "gate", "name": "Porchester Gate", "opening_hours": "Mo-Su 06:00-18:30", "place": "locality", "source": "gps+mapnoter"}}, {"type": "node", "id": 3765139177, "lat": 51.501627, "lon": -0.1805534}, {"type": "node", "id": 3765156878, "lat": 51.5016683, "lon": -0.177161}, {"type": "node", "id": 3765156879, "lat": 51.5016698, "lon": -0.1770912}, {"type": "node", "id": 3765156880, "lat": 51.5016746, "lon": -0.1775055}, {"type": "node", "id": 3765156881, "lat": 51.5016757, "lon": -0.176905}, {"type": "node", "id": 3765156882, "lat": 51.5016759, "lon": -0.1775753}, {"type": "node", "id": 3765156883, "lat": 51.5016764, "lon": -0.1776038}, {"type": "node", "id": 3765156885, "lat": 51.5016825, "lon": -0.1779359}, {"type": "node", "id": 3765156887, "lat": 51.5016831, "lon": -0.1766506}, {"type": "node", "id": 3765156888, "lat": 51.5016851, "lon": -0.1779931}, {"type": "node", "id": 3765156891, "lat": 51.5016534, "lon": -0.1801701}, {"type": "node", "id": 3765156896, "lat": 51.5016501, "lon": -0.1802094}, {"type": "node", "id": 3765160635, "lat": 51.501669, "lon": -0.1771261}, {"type": "node", "id": 3765160636, "lat": 51.5016753, "lon": -0.1775404, "tags": {"barrier": "gate", "opening_hours": "Mo-Su 06:00-18:30", "place": "locality"}}, {"type": "node", "id": 3765160637, "lat": 51.5016814, "lon": -0.1767076}, {"type": "node", "id": 3765160638, "lat": 51.5016828, "lon": -0.1783107}, {"type": "node", "id": 3765160639, "lat": 51.5016838, "lon": -0.1779645}, {"type": "node", "id": 3765186562, "lat": 51.501706, "lon": -0.1761558}, {"type": "node", "id": 3765186565, "lat": 51.5017316, "lon": -0.1757836}, {"type": "node", "id": 3765186570, "lat": 51.501755, "lon": -0.1753844}, {"type": "node", "id": 3765186577, "lat": 51.5017843, "lon": -0.1750481}, {"type": "node", "id": 3765186579, "lat": 51.5018006, "lon": -0.1748349}, {"type": "node", "id": 3765186585, "lat": 51.5018132, "lon": -0.1747982}, {"type": "node", "id": 3765186590, "lat": 51.5018349, "lon": -0.1747694}, {"type": "node", "id": 3765186594, "lat": 51.5018452, "lon": -0.1743266}, {"type": "node", "id": 3765186595, "lat": 51.5018469, "lon": -0.1743708}, {"type": "node", "id": 3765186596, "lat": 51.5018539, "lon": -0.1747615}, {"type": "node", "id": 3765186600, "lat": 51.5018575, "lon": -0.1744014}, {"type": "node", "id": 3765186602, "lat": 51.5018691, "lon": -0.1747695}, {"type": "node", "id": 3765186603, "lat": 51.5018709, "lon": -0.1747276}, {"type": "node", "id": 3765186605, "lat": 51.5018744, "lon": -0.1744213}, {"type": "node", "id": 3765186606, "lat": 51.5018739, "lon": -0.1746362}, {"type": "node", "id": 3765186607, "lat": 51.5018743, "lon": -0.174609}, {"type": "node", "id": 3765186608, "lat": 51.5018839, "lon": -0.1737659}, {"type": "node", "id": 3765186609, "lat": 51.5018793, "lon": -0.1745164}, {"type": "node", "id": 3765186610, "lat": 51.5018872, "lon": -0.1744279}, {"type": "node", "id": 3765186624, "lat": 51.5020714, "lon": -0.1747826}, {"type": "node", "id": 3765189238, "lat": 51.5018702, "lon": -0.1747482, "tags": {"barrier": "gate"}}, {"type": "node", "id": 3765189240, "lat": 51.5018811, "lon": -0.1744819, "tags": {"barrier": "gate", "name": "Alexandra Gate"}}, {"type": "node", "id": 3765189246, "lat": 51.5020829, "lon": -0.1747829, "tags": {"barrier": "gate", "opening_hours": "Mo-Su 06:00-18:30"}}, {"type": "node", "id": 3765189247, "lat": 51.5020912, "lon": -0.1747831}, {"type": "node", "id": 3765189251, "lat": 51.5021075, "lon": -0.1747842}, {"type": "node", "id": 3765189252, "lat": 51.5021654, "lon": -0.1747853, "tags": {"barrier": "gate", "name": "Coalbrookdale Gates", "opening_hours": "Mo-Su 06:00-18:30", "place": "locality", "source:name": "https://www.royalparks.org.uk/parks/kensington-gardens/things-to-see-and-do/memorials,-fountains-and-statues/coalbrookdale-gates"}}, {"type": "node", "id": 3765189253, "lat": 51.5022409, "lon": -0.1747868}, {"type": "node", "id": 3765189256, "lat": 51.5022596, "lon": -0.1747872}, {"type": "node", "id": 3765190261, "lat": 51.5023228, "lon": -0.1747888}, {"type": "node", "id": 3765209068, "lat": 51.5018741, "lon": -0.1746237}, {"type": "node", "id": 3765209103, "lat": 51.5022204, "lon": -0.1747863}, {"type": "node", "id": 3765209113, "lat": 51.5022296, "lon": -0.1747865, "tags": {"barrier": "gate", "opening_hours": "Mo-Su 06:00-18:30"}}, {"type": "node", "id": 3765209149, "lat": 51.5022886, "lon": -0.1747876, "tags": {"barrier": "gate", "opening_hours": "Mo-Su 06:00-18:30"}}, {"type": "node", "id": 3765215749, "lat": 51.5016998, "lon": -0.1783126}, {"type": "node", "id": 3765215750, "lat": 51.5018725, "lon": -0.1746818, "tags": {"barrier": "gate", "bicycle": "yes", "bus": "destination", "foot": "no", "goods": "delivery", "hgv": "delivery", "motor_vehicle": "yes", "name": "Alexandra Gate", "place": "locality", "taxi": "yes"}}, {"type": "node", "id": 3765215751, "lat": 51.5018771, "lon": -0.1745595, "tags": {"barrier": "gate", "name": "Alexandra Gate"}}, {"type": "node", "id": 3765215752, "lat": 51.5019013, "lon": -0.1735135}, {"type": "node", "id": 3765215754, "lat": 51.5019247, "lon": -0.1735027}, {"type": "node", "id": 3765220266, "lat": 51.5024364, "lon": -0.1748141}, {"type": "node", "id": 3824505644, "lat": 51.5021862, "lon": -0.165466}, {"type": "node", "id": 3922688289, "lat": 51.5105271, "lon": -0.1717252, "tags": {"barrier": "gate", "opening_hours": "Mo-Su 06:00-18:30"}}, {"type": "node", "id": 4060278703, "lat": 51.505816, "lon": -0.1730793, "tags": {"highway": "street_lamp"}}, {"type": "node", "id": 4060278706, "lat": 51.5058938, "lon": -0.1730001}, {"type": "node", "id": 4060278710, "lat": 51.5065817, "lon": -0.1724687}, {"type": "node", "id": 4060278713, "lat": 51.5066611, "lon": -0.1724055, "tags": {"highway": "street_lamp"}}, {"type": "node", "id": 4060278715, "lat": 51.5067583, "lon": -0.1712331}, {"type": "node", "id": 4060278716, "lat": 51.50678, "lon": -0.1711352}, {"type": "node", "id": 4060278725, "lat": 51.5071187, "lon": -0.1708285, "tags": {"barrier": "gate", "opening_hours": "Mo-Su 06:00-18:30"}}, {"type": "node", "id": 4060278728, "lat": 51.5071397, "lon": -0.1707926}, {"type": "node", "id": 4060278729, "lat": 51.5071397, "lon": -0.1708281}, {"type": "node", "id": 4060278731, "lat": 51.5071481, "lon": -0.1707704}, {"type": "node", "id": 4060278732, "lat": 51.5071627, "lon": -0.170759}, {"type": "node", "id": 4060278734, "lat": 51.5071798, "lon": -0.1707604}, {"type": "node", "id": 4060278735, "lat": 51.5071919, "lon": -0.1706424}, {"type": "node", "id": 4060278736, "lat": 51.5072136, "lon": -0.1707825}, {"type": "node", "id": 4060278737, "lat": 51.507219, "lon": -0.1707618, "tags": {"barrier": "gate", "opening_hours": "Mo-Su 06:00-18:30"}}, {"type": "node", "id": 4060278743, "lat": 51.508429, "lon": -0.1705972}, {"type": "node", "id": 4060278745, "lat": 51.5091213, "lon": -0.1706605}, {"type": "node", "id": 4060278747, "lat": 51.5096338, "lon": -0.1707248}, {"type": "node", "id": 4060278749, "lat": 51.509769, "lon": -0.170749}, {"type": "node", "id": 4060278750, "lat": 51.5098559, "lon": -0.1707677}, {"type": "node", "id": 4197289882, "lat": 51.5110993, "lon": -0.1730622}, {"type": "node", "id": 4197289883, "lat": 51.5109987, "lon": -0.1728786}, {"type": "node", "id": 4392878898, "lat": 51.5124031, "lon": -0.1612917}, {"type": "node", "id": 4392878899, "lat": 51.5123656, "lon": -0.1614282}, {"type": "node", "id": 4392878903, "lat": 51.5124326, "lon": -0.1588479}, {"type": "node", "id": 4392878908, "lat": 51.5114529, "lon": -0.158332}, {"type": "node", "id": 4392878914, "lat": 51.5121985, "lon": -0.1613746}, {"type": "node", "id": 4392878916, "lat": 51.5122255, "lon": -0.1611117}, {"type": "node", "id": 4392895211, "lat": 51.5113185, "lon": -0.1733123}, {"type": "node", "id": 4444845664, "lat": 51.5023322, "lon": -0.1630999, "tags": {"barrier": "gate"}}, {"type": "node", "id": 5838544967, "lat": 51.5102534, "lon": -0.1856288, "tags": {"barrier": "gate", "name": "Inverness Terrace Gate", "opening_hours": "Mo-Su 06:00-18:30", "place": "locality"}}, {"type": "node", "id": 5838544973, "lat": 51.5108557, "lon": -0.1801879, "tags": {"barrier": "gate", "foot": "permissive", "name": "Lancaster Gate", "place": "locality"}}, {"type": "node", "id": 5838550880, "lat": 51.5117422, "lon": -0.174132, "tags": {"barrier": "gate", "bicycle": "no", "foot": "permissive", "name": "Westbourne Gate", "opening_hours": "Mo-Su 06:00-18:30", "place": "locality"}}, {"type": "node", "id": 5838598620, "lat": 51.5122143, "lon": -0.1686457, "tags": {"barrier": "gate", "name": "Clarendon Gate", "place": "locality"}}, {"type": "node", "id": 5838630848, "lat": 51.5016613, "lon": -0.1800705}, {"type": "node", "id": 5838630849, "lat": 51.5016241, "lon": -0.1805974}, {"type": "node", "id": 5838630850, "lat": 51.5016154, "lon": -0.18004}, {"type": "node", "id": 5838640801, "lat": 51.5021855, "lon": -0.1856629, "tags": {"barrier": "gate", "name": "Victoria Road Gate", "opening_hours": "Mo-Su 06:00-18:30", "place": "locality"}}, {"type": "node", "id": 5973481947, "lat": 51.512123, "lon": -0.1586827, "tags": {"barrier": "gate"}}, {"type": "node", "id": 5980887010, "lat": 51.5022987, "lon": -0.1641077}, {"type": "node", "id": 7369413096, "lat": 51.5016308, "lon": -0.1805135}, {"type": "node", "id": 7394547982, "lat": 51.5033926, "lon": -0.1717999}, {"type": "node", "id": 7561148545, "lat": 51.5086484, "lon": -0.1553228}, {"type": "node", "id": 7561148555, "lat": 51.5081893, "lon": -0.1548743}, {"type": "node", "id": 7567853620, "lat": 51.5114456, "lon": -0.1583669}, {"type": "node", "id": 7567893686, "lat": 51.5093145, "lon": -0.1566225}, {"type": "node", "id": 7567893687, "lat": 51.509326, "lon": -0.1565712}, {"type": "node", "id": 7567893688, "lat": 51.509472, "lon": -0.1567126}, {"type": "node", "id": 7567893689, "lat": 51.5090503, "lon": -0.1560474}, {"type": "node", "id": 7567919396, "lat": 51.5084357, "lon": -0.155049}, {"type": "node", "id": 7567987759, "lat": 51.5041818, "lon": -0.1524859, "tags": {"barrier": "gate", "bicycle": "yes", "foot": "yes"}}, {"type": "node", "id": 7567996229, "lat": 51.504696, "lon": -0.1522629, "tags": {"barrier": "gate"}}, {"type": "node", "id": 7710485220, "lat": 51.5024212, "lon": -0.1874404, "tags": {"barrier": "gate", "opening_hours": "Mo-Su 06:00-18:30"}}, {"type": "node", "id": 7813413876, "lat": 51.511991, "lon": -0.1586033}, {"type": "node", "id": 7890249155, "lat": 51.5035909, "lon": -0.1520878}, {"type": "node", "id": 7938078383, "lat": 51.5025766, "lon": -0.1584358, "tags": {"access": "no", "barrier": "gate", "foot": "yes"}}, {"type": "node", "id": 7938078384, "lat": 51.5025661, "lon": -0.1586332, "tags": {"access": "no", "barrier": "gate", "foot": "yes"}}, {"type": "node", "id": 8975760356, "lat": 51.5118804, "lon": -0.1723431}, {"type": "node", "id": 8975760357, "lat": 51.5118876, "lon": -0.1721182}, {"type": "node", "id": 8975760358, "lat": 51.5118976, "lon": -0.1721178}, {"type": "node", "id": 8975760359, "lat": 51.5118704, "lon": -0.1723373}, {"type": "node", "id": 10588117221, "lat": 51.5104998, "lon": -0.1825489}, {"type": "node", "id": 10972186739, "lat": 51.5037081, "lon": -0.1521322}, {"type": "node", "id": 10972186740, "lat": 51.5030996, "lon": -0.153252}, {"type": "node", "id": 11225679240, "lat": 51.5016327, "lon": -0.1804839}, {"type": "node", "id": 11225679241, "lat": 51.5016394, "lon": -0.1803786}, {"type": "node", "id": 11225679242, "lat": 51.5016459, "lon": -0.1802759}, {"type": "node", "id": 11225679243, "lat": 51.5016491, "lon": -0.1802247}, {"type": "node", "id": 11230828266, "lat": 51.5118723, "lon": -0.1723152, "tags": {"barrier": "gate"}}, {"type": "node", "id": 11776311676, "lat": 51.5066691, "lon": -0.1529085}, {"type": "node", "id": 11776311677, "lat": 51.5064456, "lon": -0.1526808}, {"type": "node", "id": 11776311682, "lat": 51.5072367, "lon": -0.1536012}, {"type": "node", "id": 11776311683, "lat": 51.5079004, "lon": -0.1544693}, {"type": "node", "id": 11776311761, "lat": 51.5123533, "lon": -0.1599969}, {"type": "node", "id": 11776311776, "lat": 51.5129435, "lon": -0.1617413}, {"type": "node", "id": 11776311777, "lat": 51.5124271, "lon": -0.161248}, {"type": "node", "id": 11776311843, "lat": 51.5026013, "lon": -0.158428}, {"type": "node", "id": 11936410303, "lat": 51.5106367, "lon": -0.1815297}, {"type": "node", "id": 11936410304, "lat": 51.5111357, "lon": -0.1784722}, {"type": "node", "id": 11936422667, "lat": 51.5118857, "lon": -0.1724177}, {"type": "node", "id": 11936422668, "lat": 51.511895, "lon": -0.1724287}, {"type": "node", "id": 11936457843, "lat": 51.510925, "lon": -0.1797988}, {"type": "node", "id": 11936475569, "lat": 51.5118966, "lon": -0.1724442}, {"type": "way", "id": 3986346, "nodes": [3765190261, 3765209149, 3765189256, 3765189253, 3765209113, 3765209103, 3765189252, 3765189251, 3765189247, 3765189246, 3765186624, 3765186602, 3765186596, 3765186590, 3765186585, 3765186579, 3765186577, 3765186570, 3765186565, 3765186562, 3765156887, 3765160637, 3765156881, 3765156879, 3765160635, 3765156878, 3765156880, 3765160636, 3765156882, 3765156883, 3765156885, 3765160639, 3765156888, 3765160638, 3765215749, 20821183, 5838630850, 5838630848, 3765156891, 3765156896, 11225679243, 2198682903, 11225679242, 11225679241, 1109765920, 11225679240, 7369413096, 3765139177, 5838630849, 1436367924, 1436368100, 1436361337, 1109765917, 1436361238, 1109765916, 20821185, 5838640801, 1436511768, 7710485220, 20821141, 1436511736, 20821142, 3054882685, 20821143, 1699764452, 1699764471, 1699764478, 1699764490, 1699764500, 1699764485, 1699764466, 20821144, 1699764523, 331421032, 1699764531, 725292344, 725292429, 725292334, 1699764568, 725292299, 331421031, 20821146, 20821147, 1699764754, 834349201, 20821152, 764881525, 20821153, 20821155, 20821156, 20821158, 3679163773, 3679163785, 5838544967, 3679166320, 20821159, 10588117221, 11936410303, 5838544973, 11936457843, 11936410304, 20821161, 298299052, 21494027, 20821162, 5838550880, 2763549311, 207445792, 20821168, 1436642338, 4392895211, 207454651, 4197289882, 4197289883, 1436642449, 1973787097, 3922688289, 1973787095, 20821169, 1973787094, 237012676, 4060278750, 4060278749, 4060278747, 207477691, 4060278745, 4060278743, 1436408680, 237012663, 4060278735, 237012672, 4060278737, 4060278736, 4060278734, 4060278732, 4060278731, 4060278728, 4060278729, 4060278725, 20821171, 1973962705, 4060278716, 1504531858, 4060278715, 237012656, 20821172, 255681108, 20821174, 4060278713, 1737450669, 4060278710, 1737433651, 4060278706, 1974138102, 20947304, 4060278703, 20821176, 86119745, 20821177, 1973883240, 20821178, 1973883218, 20821179, 20821180, 3765220266, 3765190261], "tags": {"access": "yes", "heritage": "2", "heritage:operator": "Historic England", "heritage:operator:wikidata": "Q19604421", "heritage:website": "https://historicengland.org.uk/listing/the-list/list-entry/1000340", "historic": "park", "leisure": "park", "listed_status": "Grade I", "name": "Kensington Gardens", "name:ru": "\u041a\u0435\u043d\u0441\u0438\u043d\u0433\u0442\u043e\u043d\u0441\u043a\u0438\u0435 \u0441\u0430\u0434\u044b", "name:uk": "\u041a\u0435\u043d\u0441\u0456\u043d\u0433\u0442\u043e\u043d\u0441\u044c\u043a\u0456 \u0441\u0430\u0434\u0438", "operator": "The Royal Parks", "operator:wikidata": "Q7761716", "ref:GB:nhle": "1000340", "wikidata": "Q822607", "wikipedia": "en:Kensington Gardens"}}, {"type": "way", "id": 230320621, "nodes": [2388382246, 2388382244, 2388382243, 2388382242, 2388382245, 2388382250, 7394547982, 2388382249, 2388382248, 2388382247, 2388382246], "tags": {"access": "private", "contact:website": "http://www.royalparks.org.uk/parks/hyde-park/sport-in-hyde-park/football-pitches-in-hyde-park", "fee": "yes", "leisure": "park", "name": "Old Football Pitches"}}, {"type": "way", "id": 372975520, "nodes": [5973481947, 7813413876, 2558339871, 7567853620, 4392878908, 20821199, 247393224, 671350344, 7567893688, 671350346, 7567893686, 7567893687, 7567893689, 734984888, 671350287, 7561148545, 7567919396, 452413249, 207610513, 7561148555, 11776311683, 247392315, 11776311682, 11776311676, 11776311677, 207609227, 20821192, 735473609, 735473604, 735473600, 207609226, 671360987, 207609224, 7567996229, 1973754694, 207609223, 7567987759, 1961861440, 1961861413, 20947353, 1973754686, 207609221, 1973754672, 236952247, 236952245, 236952243, 1349324847, 236952241, 20947352, 10972186739, 7890249155, 20947351, 20947350, 1961872705, 10972186740, 1961872707, 1961872725, 20821191, 1974138099, 207631298, 207605987, 1974138089, 20947348, 1974138093, 11776311843, 1974138078, 7938078383, 2837760388, 26389825, 2837760387, 7938078384, 1974138067, 1974138082, 1974138086, 1974138073, 3034935545, 1974138064, 1974138030, 1436218855, 1974138026, 1974138035, 1974138024, 1668567586, 1974137909, 1974138007, 1974138021, 387796890, 4444845664, 5980887010, 20821190, 3824505644, 387798023, 387798024, 20947337, 20947336, 1974137921, 2686374474, 2686374473, 20821188, 1973882995, 207562678, 1973882974, 3765215754, 3765215752, 3765186608, 3765186594, 3765186595, 3765186600, 3765186605, 3765186610, 3765189240, 3765186609, 3765215751, 3765186607, 3765209068, 3765186606, 3765215750, 3765186603, 3765189238, 3765186602, 3765186624, 3765189246, 3765189247, 3765189251, 3765189252, 3765209103, 3765209113, 3765189253, 3765189256, 3765209149, 3765190261, 3765220266, 20821180, 20821179, 1973883218, 20821178, 1973883240, 20821177, 86119745, 20821176, 4060278703, 20947304, 1974138102, 4060278706, 1737433651, 4060278710, 1737450669, 4060278713, 20821174, 255681108, 20821172, 237012656, 4060278715, 1504531858, 4060278716, 1973962705, 20821171, 4060278725, 4060278729, 4060278728, 4060278731, 4060278732, 4060278734, 4060278736, 4060278737, 237012672, 4060278735, 237012663, 1436408680, 4060278743, 4060278745, 207477691, 4060278747, 4060278749, 4060278750, 237012676, 1973787094, 20821169, 1973787095, 3922688289, 1973787097, 1436642449, 4197289883, 4197289882, 207454651, 4392895211, 1436642338, 20821168, 207445792, 2763549311, 5838550880, 11936475569, 11936422668, 11936422667, 1974253515, 8975760356, 8975760359, 11230828266, 3287719969, 3287719970, 8975760357, 8975760358, 1974253518, 1974253521, 5838598620, 20821198, 3073841718, 20821197, 207458575, 11776311776, 207458574, 20821196, 11776311777, 4392878898, 4392878899, 4392878914, 4392878916, 207458571, 11776311761, 2558339896, 20821195, 4392878903, 207460763, 5973481947], "tags": {"access": "yes", "addr:city": "London", "heritage": "2", "heritage:operator": "he", "heritage:website": "https://historicengland.org.uk/listing/the-list/list-entry/1000814", "historic": "park", "leisure": "park", "listed_status": "Grade I", "name": "Hyde Park", "name:en": "Hyde Park", "name:he": "\u05d4\u05d9\u05d9\u05d3 \u05e4\u05d0\u05e8\u05e7", "name:hi": "\u0939\u093e\u0907\u0921 \u092a\u093e\u0930\u094d\u0915", "name:ja": "\u30cf\u30a4\u30c9\u30d1\u30fc\u30af", "name:ru": "\u0413\u0430\u0439\u0434-\u043f\u0430\u0440\u043a", "name:uk": "\u0413\u0430\u0439\u0434-\u043f\u0430\u0440\u043a", "name:zh": "\u6d77\u5fb7\u516c\u56ed", "operator": "The Royal Parks", "operator:wikidata": "Q7761716", "operator:wikipedia": "en:The Royal Parks", "ref:GB:nhle": "1000814", "tourism": "attraction", "wheelchair": "yes", "wikidata": "Q123738", "wikipedia": "en:Hyde Park, London"}}]}